pure_pynacl/__init__.py
pure_pynacl/tweetnacl.py
pure_pynacl-1.0.0.dist-info/METADATA
pure_pynacl-1.0.0.dist-info/WHEEL
pure_pynacl-1.0.0.dist-info/top_level.txt
pure_pynacl-1.0.0.dist-info/RECORD
