Metadata-Version: 2.1
Name: pure-pynacl
Version: 1.0.0
Summary: Pure python implementation of TweetNaCl
Author-email: Justin Findlay <justin@findlay.space>
Project-URL: Homepage, https://github.com/jfindlay/pure_pynacl/
Project-URL: Bug Tracker, https://github.com/jfindlay/pure_pynacl/issues/
Classifier: Programming Language :: Python :: 3
Classifier: License :: OSI Approved :: Apache Software License
Classifier: Operating System :: OS Independent
Requires-Python: >=3.8
